{"stats":{"minecraft:killed":{"ars_nouveau:drygmy":1,"minecraft:salmon":3,"born_in_chaos_v1:decrepit_skeleton":1,"born_in_chaos_v1:maggot":1,"boliviamod:angry_achale":5,"minecraft:donkey":1,"minecraft:zombie":4,"alexsmobs:terrapin":1,"born_in_chaos_v1:corpse_fly":9,"born_in_chaos_v1:corpse_fish":2,"boliviamod:angry_yararina":2},"minecraft:dropped":{"quark:hollow_cherry_log":1,"minecraft:allium":13,"minecraft:charcoal":2,"minecraft:wooden_axe":2,"minecraft:writable_book":1,"minecraft:wooden_pickaxe":2},"minecraft:mined":{"minecraft:acacia_leaves":1,"iceandfire:silver_ore":21,"minecraft:dark_oak_leaves":1,"minecraft:cherry_log":5,"minecraft:dark_oak_log":15,"minecraft:torch":2,"minecraft:crafting_table":6,"minecraft:granite":3,"minecraft:acacia_log":6,"minecraft:grass_block":1,"minecraft:campfire":1,"quark:hollow_cherry_log":1,"minecraft:copper_ore":30,"minecraft:cobblestone":2,"minecraft:spruce_leaves":1,"ars_nouveau:sourceberry_bush":16,"minecraft:sugar_cane":3,"minecraft:pink_petals":2,"minecraft:large_fern":1,"minecraft:seagrass":2,"farmersdelight:wild_onions":6,"ars_nouveau:blue_archwood_log":15,"minecraft:furnace":2,"minecraft:iron_ore":5,"minecraft:spruce_log":33,"minecraft:pumpkin":12,"minecraft:copper_block":1,"create:asurine":3,"minecraft:grass":52,"minecraft:oak_log":4,"minecraft:coal_ore":116,"minecraft:dirt":2,"minecraft:stone":228,"minecraft:oak_leaves":4,"minecraft:redstone_wall_torch":2,"minecraft:fern":4,"create:zinc_ore":11},"minecraft:broken":{"minecraft:stone_pickaxe":1,"minecraft:stone_axe":1},"minecraft:crafted":{"iceandfire:silver_ingot":12,"minecraft:crafting_table":3,"minecraft:spruce_planks":120,"minecraft:wooden_pickaxe":3,"minecraft:furnace":2,"minecraft:cooked_salmon":3,"minecraft:copper_ingot":14,"minecraft:stone_axe":4,"minecraft:air":0,"iceandfire:armor_silver_metal_chestplate":1,"minecraft:shield":1,"minecraft:stick":36,"minecraft:iron_ingot":4,"minecraft:iron_pickaxe":1,"minecraft:stone_pickaxe":5,"minecraft:wooden_axe":1,"minecraft:stone_sword":1,"minecraft:copper_block":1,"minecraft:torch":28,"minecraft:dark_oak_planks":32},"minecraft:used":{"minecraft:writable_book":1,"minecraft:stone_sword":46,"minecraft:stone_pickaxe":366,"minecraft:copper_block":1,"minecraft:wooden_pickaxe":19,"minecraft:spruce_planks":5,"minecraft:cooked_salmon":1,"minecraft:rotten_flesh":5,"minecraft:torch":9,"farmersdelight:onion":8,"minecraft:crafting_table":7,"minecraft:spruce_log":2,"iceandfire:armor_silver_metal_chestplate":1,"minecraft:redstone_torch":1,"born_in_chaos_v1:corpse_maggot":13,"minecraft:iron_pickaxe":38,"create:asurine":3,"minecraft:stone_axe":176,"minecraft:cobblestone":99,"born_in_chaos_v1:rotten_fish":1,"minecraft:furnace":4,"ars_nouveau:sourceberry_bush":19,"alexsmobs:animal_dictionary":1},"minecraft:killed_by":{"alexsmobs:gelada_monkey":1},"minecraft:custom":{"enigmaticlegacy:play_time_with_seven_curses":0,"minecraft:interact_with_furnace":33,"minecraft:mob_kills":30,"enigmaticlegacy:play_time_without_seven_curses":59349,"minecraft:interact_with_crafting_table":25,"minecraft:leave_game":4,"minecraft:time_since_death":24353,"minecraft:climb_one_cm":97,"minecraft:time_since_rest":24552,"minecraft:damage_taken":1190,"minecraft:sprint_one_cm":157609,"minecraft:walk_one_cm":468133,"minecraft:drop":8,"minecraft:damage_dealt":5102,"minecraft:swim_one_cm":28316,"minecraft:fly_one_cm":369504,"minecraft:open_chest":4,"minecraft:crouch_one_cm":29066,"minecraft:play_time":59620,"minecraft:deaths":3,"minecraft:sneak_time":4780,"minecraft:walk_under_water_one_cm":11813,"minecraft:jump":1264,"minecraft:walk_on_water_one_cm":5525,"minecraft:total_world_time":59620,"minecraft:fall_one_cm":35036},"minecraft:picked_up":{"minecraft:wooden_axe":1,"minecraft:pink_petals":5,"born_in_chaos_v1:corpse_maggot":13,"minecraft:charcoal":2,"minecraft:crafting_table":6,"minecraft:allium":13,"boliviamod:living_bark":13,"minecraft:salmon":3,"minecraft:leather":1,"minecraft:copper_block":1,"minecraft:wooden_pickaxe":1,"create:raw_zinc":11,"minecraft:oak_log":4,"minecraft:dirt":3,"boliviamod:yararina_scale":2,"minecraft:raw_copper":101,"minecraft:wheat_seeds":6,"minecraft:iron_ingot":1,"minecraft:redstone_torch":2,"minecraft:sugar_cane":4,"minecraft:birch_sapling":1,"minecraft:acacia_sapling":1,"minecraft:furnace":2,"minecraft:raw_iron":5,"born_in_chaos_v1:shattered_skull":1,"minecraft:pumpkin":12,"minecraft:torch":2,"minecraft:acacia_log":6,"ars_nouveau:blue_archwood_log":15,"minecraft:cherry_log":4,"sophisticatedbackpacks:iron_backpack":1,"minecraft:spruce_log":33,"minecraft:dark_oak_log":15,"minecraft:rotten_flesh":5,"quark:hollow_cherry_log":2,"farmersdelight:onion":6,"minecraft:writable_book":1,"minecraft:granite":3,"create:asurine":3,"ars_nouveau:sourceberry_bush":34,"born_in_chaos_v1:rotten_fish":2,"minecraft:coal":154,"iceandfire:raw_silver":20,"minecraft:cobblestone":226}},"DataVersion":3465}